arkindex_base_worker-0.5.0.dist-info/licenses/LICENSE
arkindex_worker/__init__.py
arkindex_worker/cache.py
arkindex_worker/image.py
arkindex_worker/models.py
arkindex_worker/utils.py
arkindex_worker/worker/__init__.py
arkindex_worker/worker/base.py
arkindex_worker/worker/classification.py
arkindex_worker/worker/corpus.py
arkindex_worker/worker/dataset.py
arkindex_worker/worker/element.py
arkindex_worker/worker/entity.py
arkindex_worker/worker/image.py
arkindex_worker/worker/metadata.py
arkindex_worker/worker/process.py
arkindex_worker/worker/task.py
arkindex_worker/worker/training.py
arkindex_worker/worker/transcription.py
examples/standalone/python/worker.py
examples/tooled/python/worker.py
hooks/pre_gen_project.py
tests/__init__.py
tests/conftest.py
tests/test_base_worker.py
tests/test_cache.py
tests/test_dataset_worker.py
tests/test_element.py
tests/test_image.py
tests/test_merge.py
tests/test_utils.py
tests/test_elements_worker/__init__.py
tests/test_elements_worker/test_classification.py
tests/test_elements_worker/test_cli.py
tests/test_elements_worker/test_corpus.py
tests/test_elements_worker/test_dataset.py
tests/test_elements_worker/test_element.py
tests/test_elements_worker/test_element_create_multiple.py
tests/test_elements_worker/test_element_create_single.py
tests/test_elements_worker/test_element_list_children.py
tests/test_elements_worker/test_element_list_parents.py
tests/test_elements_worker/test_entity.py
tests/test_elements_worker/test_image.py
tests/test_elements_worker/test_metadata.py
tests/test_elements_worker/test_process.py
tests/test_elements_worker/test_task.py
tests/test_elements_worker/test_training.py
tests/test_elements_worker/test_transcription_create.py
tests/test_elements_worker/test_transcription_create_with_elements.py
tests/test_elements_worker/test_transcription_list.py
tests/test_elements_worker/test_worker.py
worker-demo/tests/__init__.py
worker-demo/tests/conftest.py
worker-demo/tests/test_worker.py
worker-demo/worker_demo/__init__.py
worker-demo/worker_demo/worker.py
arkindex_base_worker-0.5.0.dist-info/METADATA
arkindex_base_worker-0.5.0.dist-info/WHEEL
arkindex_base_worker-0.5.0.dist-info/top_level.txt
arkindex_base_worker-0.5.0.dist-info/RECORD
