Metadata-Version: 2.4
Name: arkindex-base-worker
Version: 0.5.0
Summary: Base Worker to easily build Arkindex ML workflows
Author-email: Teklia <contact@teklia.com>
Maintainer-email: Teklia <contact@teklia.com>
License: MIT License
Project-URL: Homepage, https://workers.arkindex.org
Project-URL: Documentation, https://workers.arkindex.org
Project-URL: Repository, https://gitlab.teklia.com/workers/base-worker
Project-URL: Bug Tracker, https://gitlab.teklia.com/workers/base-worker/issues
Project-URL: Authors, https://teklia.com
Keywords: python
Classifier: Development Status :: 5 - Production/Stable
Classifier: License :: OSI Approved :: MIT License
Classifier: Programming Language :: Python :: 3 :: Only
Classifier: Programming Language :: Python :: 3.10
Classifier: Programming Language :: Python :: 3.11
Classifier: Programming Language :: Python :: 3.12
Requires-Python: >=3.10
License-File: LICENSE
Requires-Dist: humanize==4.12.3
Requires-Dist: peewee~=3.17
Requires-Dist: Pillow==11.3.0
Requires-Dist: python-gnupg==0.5.4
Requires-Dist: shapely==2.0.6
Requires-Dist: teklia-toolbox==0.1.11
Requires-Dist: zstandard==0.23.0
Provides-Extra: tests
Requires-Dist: pytest==8.3.5; extra == "tests"
Requires-Dist: pytest-mock==3.14.0; extra == "tests"
Requires-Dist: pytest-responses==0.5.1; extra == "tests"
Dynamic: license-file
